{
  "annotations": {
    "list": [
      {
        "builtIn": 1,
        "datasource": {
          "type": "datasource",
          "uid": "grafana"
        },
        "enable": true,
        "hide": true,
        "iconColor": "rgba(0, 211, 255, 1)",
        "name": "Annotations & Alerts",
        "type": "dashboard"
      },
      {
        "datasource": {
          "type": "prometheus",
          "uid": "P3CCD15422F6EB158"
        },
        "enable": true,
        "hide": true,
        "iconColor": "rgba(0, 211, 255, 1)",
        "name": "Annotations & Alerts",
        "type": "dashboard"
      }
    ]
  },
  "description": "Dashboard for applications that use https://github.com/ansrivas/fiberprometheus",
  "editable": true,
  "fiscalYearStartMonth": 0,
  "gnetId": 14331,
  "graphTooltip": 1,
  "id": 7,
  "links": [],
  "panels": [
    {
      "collapsed": false,
      "gridPos": {
        "h": 1,
        "w": 24,
        "x": 0,
        "y": 0
      },
      "id": 48,
      "panels": [],
      "repeat": "datasource",
      "repeatDirection": "h",
      "title": "Utilities",
      "type": "row"
    },
    {
      "datasource": {
        "type": "prometheus",
        "uid": "P3CCD15422F6EB158"
      },
      "fieldConfig": {
        "defaults": {
          "color": {
            "mode": "thresholds"
          },
          "mappings": [],
          "thresholds": {
            "mode": "absolute",
            "steps": [
              {
                "color": "green",
                "value": null
              },
              {
                "color": "red",
                "value": 80
              }
            ]
          },
          "unit": "percent"
        },
        "overrides": []
      },
      "gridPos": {
        "h": 6,
        "w": 6,
        "x": 0,
        "y": 1
      },
      "id": 49,
      "options": {
        "colorMode": "value",
        "graphMode": "area",
        "justifyMode": "auto",
        "orientation": "auto",
        "reduceOptions": {
          "calcs": [
            "lastNotNull"
          ],
          "fields": "",
          "values": false
        },
        "showPercentChange": false,
        "textMode": "auto",
        "wideLayout": true
      },
      "pluginVersion": "10.4.1",
      "targets": [
        {
          "datasource": {
            "type": "prometheus",
            "uid": "P3CCD15422F6EB158"
          },
          "editorMode": "code",
          "expr": "sum(rate(container_cpu_system_seconds_total{id=\"/\"}[1m]))",
          "instant": false,
          "legendFormat": "__auto",
          "range": true,
          "refId": "A"
        },
        {
          "datasource": {
            "type": "prometheus",
            "uid": "P3CCD15422F6EB158"
          },
          "editorMode": "code",
          "expr": "sum(rate(container_cpu_system_seconds_total[1m]))",
          "hide": false,
          "instant": false,
          "legendFormat": "__auto",
          "range": true,
          "refId": "B"
        },
        {
          "datasource": {
            "type": "prometheus",
            "uid": "P3CCD15422F6EB158"
          },
          "editorMode": "code",
          "expr": "sum(rate(process_cpu_seconds_total[$__rate_interval])) * 100",
          "hide": false,
          "instant": false,
          "legendFormat": "__auto",
          "range": true,
          "refId": "C"
        },
        {
          "datasource": {
            "type": "prometheus",
            "uid": "P3CCD15422F6EB158"
          },
          "editorMode": "code",
          "expr": "sum(rate(container_cpu_system_seconds_total{name=~\".+\"}[1m])) + sum(rate(container_cpu_system_seconds_total{id=\"/\"}[1m])) + sum(rate(process_cpu_seconds_total[1m]))",
          "hide": false,
          "instant": false,
          "legendFormat": "__auto",
          "range": true,
          "refId": "D"
        },
        {
          "datasource": {
            "type": "prometheus",
            "uid": "P3CCD15422F6EB158"
          },
          "editorMode": "code",
          "expr": "sum(rate(container_cpu_system_seconds_total{name=~\".+\"}[1m]))",
          "hide": false,
          "instant": false,
          "legendFormat": "__auto",
          "range": true,
          "refId": "E"
        }
      ],
      "title": "CPU Usage",
      "type": "stat"
    },
    {
      "datasource": {
        "type": "prometheus",
        "uid": "P3CCD15422F6EB158"
      },
      "fieldConfig": {
        "defaults": {
          "color": {
            "mode": "thresholds"
          },
          "mappings": [],
          "thresholds": {
            "mode": "absolute",
            "steps": [
              {
                "color": "green",
                "value": null
              },
              {
                "color": "red",
                "value": 80
              }
            ]
          },
          "unit": "percent"
        },
        "overrides": []
      },
      "gridPos": {
        "h": 6,
        "w": 6,
        "x": 6,
        "y": 1
      },
      "id": 50,
      "options": {
        "colorMode": "value",
        "graphMode": "area",
        "justifyMode": "auto",
        "orientation": "auto",
        "reduceOptions": {
          "calcs": [
            "lastNotNull"
          ],
          "fields": "",
          "values": false
        },
        "showPercentChange": false,
        "textMode": "auto",
        "wideLayout": true
      },
      "pluginVersion": "10.4.1",
      "targets": [
        {
          "datasource": {
            "type": "prometheus",
            "uid": "P3CCD15422F6EB158"
          },
          "editorMode": "code",
          "expr": "100 * (1 - (node_filesystem_avail_bytes{device=\"/dev/vda1\", mountpoint=\"/etc/hostname\"} / node_filesystem_size_bytes{device=\"/dev/vda1\", mountpoint=\"/etc/hostname\"}))",
          "instant": false,
          "legendFormat": "__auto",
          "range": true,
          "refId": "A"
        }
      ],
      "title": "Disk Usage",
      "type": "stat"
    },
    {
      "datasource": {
        "type": "prometheus",
        "uid": "P3CCD15422F6EB158"
      },
      "fieldConfig": {
        "defaults": {
          "color": {
            "mode": "thresholds"
          },
          "mappings": [],
          "thresholds": {
            "mode": "absolute",
            "steps": [
              {
                "color": "green",
                "value": null
              },
              {
                "color": "red",
                "value": 4096
              }
            ]
          },
          "unit": "decmbytes"
        },
        "overrides": []
      },
      "gridPos": {
        "h": 6,
        "w": 6,
        "x": 12,
        "y": 1
      },
      "id": 51,
      "options": {
        "minVizHeight": 75,
        "minVizWidth": 75,
        "orientation": "auto",
        "reduceOptions": {
          "calcs": [
            "lastNotNull"
          ],
          "fields": "",
          "values": false
        },
        "showThresholdLabels": false,
        "showThresholdMarkers": true,
        "sizing": "auto"
      },
      "pluginVersion": "10.4.1",
      "targets": [
        {
          "datasource": {
            "type": "prometheus",
            "uid": "P3CCD15422F6EB158"
          },
          "editorMode": "code",
          "expr": "sum(node_memory_MemAvailable_bytes - node_memory_MemFree_bytes)/1000000",
          "instant": false,
          "legendFormat": "__auto",
          "range": true,
          "refId": "A"
        }
      ],
      "title": "Memory Usage",
      "type": "gauge"
    },
    {
      "datasource": {
        "type": "prometheus",
        "uid": "P3CCD15422F6EB158"
      },
      "fieldConfig": {
        "defaults": {
          "color": {
            "mode": "palette-classic"
          },
          "custom": {
            "axisBorderShow": false,
            "axisCenteredZero": false,
            "axisColorMode": "text",
            "axisLabel": "",
            "axisPlacement": "auto",
            "barAlignment": 0,
            "drawStyle": "line",
            "fillOpacity": 0,
            "gradientMode": "none",
            "hideFrom": {
              "legend": false,
              "tooltip": false,
              "viz": false
            },
            "insertNulls": false,
            "lineInterpolation": "linear",
            "lineWidth": 1,
            "pointSize": 5,
            "scaleDistribution": {
              "type": "linear"
            },
            "showPoints": "auto",
            "spanNulls": false,
            "stacking": {
              "group": "A",
              "mode": "none"
            },
            "thresholdsStyle": {
              "mode": "off"
            }
          },
          "mappings": [],
          "thresholds": {
            "mode": "absolute",
            "steps": [
              {
                "color": "green",
                "value": null
              },
              {
                "color": "red",
                "value": 80
              }
            ]
          },
          "unit": "decmbytes"
        },
        "overrides": []
      },
      "gridPos": {
        "h": 6,
        "w": 6,
        "x": 18,
        "y": 1
      },
      "id": 52,
      "options": {
        "legend": {
          "calcs": [],
          "displayMode": "list",
          "placement": "bottom",
          "showLegend": true
        },
        "tooltip": {
          "mode": "single",
          "sort": "none"
        }
      },
      "targets": [
        {
          "datasource": {
            "type": "prometheus",
            "uid": "P3CCD15422F6EB158"
          },
          "editorMode": "code",
          "expr": "rate(node_network_receive_bytes_total{device=\"eth0\"}[$__rate_interval]) / 1000000",
          "instant": false,
          "legendFormat": "network receive (mbps)",
          "range": true,
          "refId": "A"
        },
        {
          "datasource": {
            "type": "prometheus",
            "uid": "P3CCD15422F6EB158"
          },
          "editorMode": "code",
          "expr": "rate(node_network_transmit_bytes_total{device=\"eth0\"}[$__rate_interval]) / 1000000",
          "hide": false,
          "instant": false,
          "legendFormat": "network sent (mbps)",
          "range": true,
          "refId": "B"
        }
      ],
      "title": "Network Usage",
      "type": "timeseries"
    },
    {
      "datasource": {
        "type": "prometheus",
        "uid": "P3CCD15422F6EB158"
      },
      "fieldConfig": {
        "defaults": {
          "color": {
            "mode": "thresholds"
          },
          "mappings": [],
          "thresholds": {
            "mode": "absolute",
            "steps": [
              {
                "color": "green",
                "value": null
              },
              {
                "color": "red",
                "value": 80
              }
            ]
          }
        },
        "overrides": []
      },
      "gridPos": {
        "h": 6,
        "w": 6,
        "x": 0,
        "y": 7
      },
      "id": 53,
      "options": {
        "colorMode": "value",
        "graphMode": "area",
        "justifyMode": "auto",
        "orientation": "auto",
        "reduceOptions": {
          "calcs": [
            "lastNotNull"
          ],
          "fields": "",
          "values": false
        },
        "showPercentChange": false,
        "textMode": "auto",
        "wideLayout": true
      },
      "pluginVersion": "10.4.1",
      "targets": [
        {
          "datasource": {
            "type": "prometheus",
            "uid": "P3CCD15422F6EB158"
          },
          "editorMode": "code",
          "expr": "go_threads{job=\"banking-app\"}",
          "instant": false,
          "legendFormat": "__auto",
          "range": true,
          "refId": "A"
        }
      ],
      "title": "Go Threads",
      "type": "stat"
    },
    {
      "datasource": {
        "type": "prometheus",
        "uid": "P3CCD15422F6EB158"
      },
      "fieldConfig": {
        "defaults": {
          "color": {
            "mode": "thresholds"
          },
          "mappings": [],
          "thresholds": {
            "mode": "absolute",
            "steps": [
              {
                "color": "green",
                "value": null
              },
              {
                "color": "red",
                "value": 80
              }
            ]
          }
        },
        "overrides": []
      },
      "gridPos": {
        "h": 6,
        "w": 6,
        "x": 6,
        "y": 7
      },
      "id": 54,
      "options": {
        "colorMode": "value",
        "graphMode": "area",
        "justifyMode": "auto",
        "orientation": "auto",
        "reduceOptions": {
          "calcs": [
            "lastNotNull"
          ],
          "fields": "",
          "values": false
        },
        "showPercentChange": false,
        "textMode": "auto",
        "wideLayout": true
      },
      "pluginVersion": "10.4.1",
      "targets": [
        {
          "datasource": {
            "type": "prometheus",
            "uid": "P3CCD15422F6EB158"
          },
          "editorMode": "code",
          "expr": "go_goroutines{instance=\"host.docker.internal:8080\",job=\"banking-app\"}",
          "instant": false,
          "legendFormat": "__auto",
          "range": true,
          "refId": "A"
        }
      ],
      "title": "Goroutines",
      "type": "stat"
    },
    {
      "datasource": {
        "type": "prometheus",
        "uid": "P3CCD15422F6EB158"
      },
      "fieldConfig": {
        "defaults": {
          "color": {
            "mode": "thresholds"
          },
          "mappings": [],
          "thresholds": {
            "mode": "absolute",
            "steps": [
              {
                "color": "green",
                "value": null
              },
              {
                "color": "red",
                "value": 80
              }
            ]
          }
        },
        "overrides": []
      },
      "gridPos": {
        "h": 6,
        "w": 6,
        "x": 12,
        "y": 7
      },
      "id": 55,
      "options": {
        "colorMode": "value",
        "graphMode": "area",
        "justifyMode": "auto",
        "orientation": "auto",
        "reduceOptions": {
          "calcs": [
            "lastNotNull"
          ],
          "fields": "",
          "values": false
        },
        "showPercentChange": false,
        "textMode": "auto",
        "wideLayout": true
      },
      "pluginVersion": "10.4.1",
      "targets": [
        {
          "datasource": {
            "type": "prometheus",
            "uid": "P3CCD15422F6EB158"
          },
          "editorMode": "code",
          "expr": "pgx_pool_total_connections{db=\"openidea_banking_app\"}",
          "instant": false,
          "legendFormat": "__auto",
          "range": true,
          "refId": "A"
        }
      ],
      "title": "DB Total Conn",
      "type": "stat"
    },
    {
      "collapsed": false,
      "datasource": {
        "type": "prometheus",
        "uid": "P3CCD15422F6EB158"
      },
      "gridPos": {
        "h": 1,
        "w": 24,
        "x": 0,
        "y": 13
      },
      "id": 41,
      "panels": [],
      "targets": [
        {
          "datasource": {
            "type": "prometheus",
            "uid": "P3CCD15422F6EB158"
          },
          "refId": "A"
        }
      ],
      "title": "Traffic",
      "type": "row"
    },
    {
      "datasource": {
        "type": "prometheus",
        "uid": "${datasource}"
      },
      "fieldConfig": {
        "defaults": {
          "color": {
            "mode": "palette-classic"
          },
          "custom": {
            "axisBorderShow": false,
            "axisCenteredZero": false,
            "axisColorMode": "text",
            "axisLabel": "",
            "axisPlacement": "auto",
            "barAlignment": 0,
            "drawStyle": "line",
            "fillOpacity": 10,
            "gradientMode": "none",
            "hideFrom": {
              "legend": false,
              "tooltip": false,
              "viz": false
            },
            "insertNulls": false,
            "lineInterpolation": "linear",
            "lineWidth": 1,
            "pointSize": 5,
            "scaleDistribution": {
              "type": "linear"
            },
            "showPoints": "never",
            "spanNulls": false,
            "stacking": {
              "group": "A",
              "mode": "none"
            },
            "thresholdsStyle": {
              "mode": "off"
            }
          },
          "mappings": [],
          "thresholds": {
            "mode": "absolute",
            "steps": [
              {
                "color": "green",
                "value": null
              },
              {
                "color": "red",
                "value": 80
              }
            ]
          },
          "unit": "short"
        },
        "overrides": []
      },
      "gridPos": {
        "h": 9,
        "w": 24,
        "x": 0,
        "y": 14
      },
      "id": 17,
      "options": {
        "legend": {
          "calcs": [],
          "displayMode": "list",
          "placement": "bottom",
          "showLegend": true
        },
        "tooltip": {
          "mode": "multi",
          "sort": "desc"
        }
      },
      "pluginVersion": "10.4.1",
      "targets": [
        {
          "application": {
            "filter": ""
          },
          "datasource": {
            "type": "prometheus",
            "uid": "${datasource}"
          },
          "editorMode": "code",
          "exemplar": true,
          "expr": "sum(rate(http_requests_total{job=~\"$job\",instance=~\"$instance\", path=~\"$handler\", namespace=~\"$namespace\"}[2m])) by (job)",
          "format": "time_series",
          "functions": [],
          "group": {
            "filter": ""
          },
          "host": {
            "filter": ""
          },
          "interval": "",
          "intervalFactor": 1,
          "item": {
            "filter": ""
          },
          "legendFormat": "{{ job }}",
          "mode": 0,
          "options": {
            "showDisabledItems": false,
            "skipEmptyValues": false
          },
          "range": true,
          "refId": "A",
          "resultFormat": "time_series",
          "table": {
            "skipEmptyValues": false
          },
          "triggers": {
            "acknowledged": 2,
            "count": true,
            "minSeverity": 3
          }
        }
      ],
      "title": "Traffic - Req/s",
      "type": "timeseries"
    },
    {
      "datasource": {
        "uid": "$datasource"
      },
      "fieldConfig": {
        "defaults": {
          "color": {
            "mode": "palette-classic"
          },
          "custom": {
            "axisBorderShow": false,
            "axisCenteredZero": false,
            "axisColorMode": "text",
            "axisLabel": "",
            "axisPlacement": "auto",
            "barAlignment": 0,
            "drawStyle": "line",
            "fillOpacity": 10,
            "gradientMode": "none",
            "hideFrom": {
              "legend": false,
              "tooltip": false,
              "viz": false
            },
            "insertNulls": false,
            "lineInterpolation": "linear",
            "lineWidth": 1,
            "pointSize": 5,
            "scaleDistribution": {
              "type": "linear"
            },
            "showPoints": "never",
            "spanNulls": false,
            "stacking": {
              "group": "A",
              "mode": "none"
            },
            "thresholdsStyle": {
              "mode": "off"
            }
          },
          "mappings": [],
          "thresholds": {
            "mode": "absolute",
            "steps": [
              {
                "color": "green",
                "value": null
              },
              {
                "color": "red",
                "value": 80
              }
            ]
          },
          "unit": "short"
        },
        "overrides": []
      },
      "gridPos": {
        "h": 9,
        "w": 24,
        "x": 0,
        "y": 23
      },
      "id": 46,
      "options": {
        "legend": {
          "calcs": [],
          "displayMode": "list",
          "placement": "bottom",
          "showLegend": true
        },
        "tooltip": {
          "mode": "multi",
          "sort": "desc"
        }
      },
      "pluginVersion": "10.4.1",
      "targets": [
        {
          "application": {
            "filter": ""
          },
          "datasource": {
            "uid": "$datasource"
          },
          "exemplar": true,
          "expr": "sum(rate(http_requests_total{job=~\"$job\",instance=~\"$instance\", path=~\"$handler\", namespace=~\"$namespace\"}[2m])) by (job, instance)",
          "format": "time_series",
          "functions": [],
          "group": {
            "filter": ""
          },
          "host": {
            "filter": ""
          },
          "interval": "",
          "intervalFactor": 1,
          "item": {
            "filter": ""
          },
          "legendFormat": "{{ job }} - {{ instance }}",
          "mode": 0,
          "options": {
            "showDisabledItems": false,
            "skipEmptyValues": false
          },
          "refId": "A",
          "resultFormat": "time_series",
          "table": {
            "skipEmptyValues": false
          },
          "triggers": {
            "acknowledged": 2,
            "count": true,
            "minSeverity": 3
          }
        }
      ],
      "title": "Traffic by instance - Req/s",
      "type": "timeseries"
    },
    {
      "datasource": {
        "type": "prometheus",
        "uid": "$datasource"
      },
      "fieldConfig": {
        "defaults": {
          "color": {
            "mode": "palette-classic"
          },
          "custom": {
            "axisBorderShow": false,
            "axisCenteredZero": false,
            "axisColorMode": "text",
            "axisLabel": "",
            "axisPlacement": "auto",
            "barAlignment": 0,
            "drawStyle": "line",
            "fillOpacity": 10,
            "gradientMode": "none",
            "hideFrom": {
              "legend": false,
              "tooltip": false,
              "viz": false
            },
            "insertNulls": false,
            "lineInterpolation": "linear",
            "lineWidth": 1,
            "pointSize": 5,
            "scaleDistribution": {
              "type": "linear"
            },
            "showPoints": "never",
            "spanNulls": false,
            "stacking": {
              "group": "A",
              "mode": "none"
            },
            "thresholdsStyle": {
              "mode": "off"
            }
          },
          "mappings": [],
          "thresholds": {
            "mode": "absolute",
            "steps": [
              {
                "color": "green",
                "value": null
              },
              {
                "color": "red",
                "value": 80
              }
            ]
          },
          "unit": "short"
        },
        "overrides": []
      },
      "gridPos": {
        "h": 9,
        "w": 24,
        "x": 0,
        "y": 32
      },
      "id": 34,
      "options": {
        "legend": {
          "calcs": [],
          "displayMode": "list",
          "placement": "bottom",
          "showLegend": true
        },
        "tooltip": {
          "mode": "multi",
          "sort": "desc"
        }
      },
      "pluginVersion": "10.4.1",
      "targets": [
        {
          "application": {
            "filter": ""
          },
          "datasource": {
            "uid": "$datasource"
          },
          "editorMode": "code",
          "exemplar": true,
          "expr": "sum(rate(http_requests_total{job=~\"$job\",instance=~\"$instance\", path=~\"$handler\", namespace=~\"$namespace\"}[2m])) by (job, method, path)",
          "format": "time_series",
          "functions": [],
          "group": {
            "filter": ""
          },
          "host": {
            "filter": ""
          },
          "interval": "",
          "intervalFactor": 1,
          "item": {
            "filter": ""
          },
          "legendFormat": "{{ job }} - {{ method }} {{handler}}",
          "mode": 0,
          "options": {
            "showDisabledItems": false,
            "skipEmptyValues": false
          },
          "range": true,
          "refId": "A",
          "resultFormat": "time_series",
          "table": {
            "skipEmptyValues": false
          },
          "triggers": {
            "acknowledged": 2,
            "count": true,
            "minSeverity": 3
          }
        }
      ],
      "title": "Traffic - Req/s by handler",
      "type": "timeseries"
    },
    {
      "collapsed": false,
      "datasource": {
        "type": "prometheus",
        "uid": "P3CCD15422F6EB158"
      },
      "gridPos": {
        "h": 1,
        "w": 24,
        "x": 0,
        "y": 41
      },
      "id": 43,
      "panels": [],
      "targets": [
        {
          "datasource": {
            "type": "prometheus",
            "uid": "P3CCD15422F6EB158"
          },
          "refId": "A"
        }
      ],
      "title": "Errors",
      "type": "row"
    },
    {
      "datasource": {
        "type": "prometheus",
        "uid": "$datasource"
      },
      "fieldConfig": {
        "defaults": {
          "color": {
            "mode": "palette-classic"
          },
          "custom": {
            "axisBorderShow": false,
            "axisCenteredZero": false,
            "axisColorMode": "text",
            "axisLabel": "",
            "axisPlacement": "auto",
            "barAlignment": 0,
            "drawStyle": "line",
            "fillOpacity": 10,
            "gradientMode": "none",
            "hideFrom": {
              "legend": false,
              "tooltip": false,
              "viz": false
            },
            "insertNulls": false,
            "lineInterpolation": "linear",
            "lineWidth": 1,
            "pointSize": 5,
            "scaleDistribution": {
              "type": "linear"
            },
            "showPoints": "never",
            "spanNulls": false,
            "stacking": {
              "group": "A",
              "mode": "none"
            },
            "thresholdsStyle": {
              "mode": "off"
            }
          },
          "mappings": [],
          "thresholds": {
            "mode": "absolute",
            "steps": [
              {
                "color": "green",
                "value": null
              },
              {
                "color": "red",
                "value": 80
              }
            ]
          },
          "unit": "percentunit"
        },
        "overrides": []
      },
      "gridPos": {
        "h": 9,
        "w": 24,
        "x": 0,
        "y": 42
      },
      "id": 35,
      "options": {
        "legend": {
          "calcs": [],
          "displayMode": "list",
          "placement": "bottom",
          "showLegend": true
        },
        "tooltip": {
          "mode": "multi",
          "sort": "desc"
        }
      },
      "pluginVersion": "10.4.1",
      "targets": [
        {
          "application": {
            "filter": ""
          },
          "datasource": {
            "uid": "$datasource"
          },
          "editorMode": "code",
          "exemplar": true,
          "expr": "sum(rate(http_requests_total{job=~\"$job\",instance=~\"$instance\", path=~\"$handler\", namespace=~\"$namespace\", status=\"500|502|503|504\"}[5m])) by (job)/sum(rate(http_requests_total{job=~\"$job\",instance=~\"$instance\", path=~\"$handler\", namespace=~\"$namespace\"}[5m])) by (job)",
          "format": "time_series",
          "functions": [],
          "group": {
            "filter": ""
          },
          "host": {
            "filter": ""
          },
          "instant": false,
          "interval": "",
          "intervalFactor": 1,
          "item": {
            "filter": ""
          },
          "legendFormat": "__auto",
          "mode": 0,
          "options": {
            "showDisabledItems": false,
            "skipEmptyValues": false
          },
          "refId": "A",
          "resultFormat": "time_series",
          "table": {
            "skipEmptyValues": false
          },
          "triggers": {
            "acknowledged": 2,
            "count": true,
            "minSeverity": 3
          }
        }
      ],
      "title": "Errors - % (5xx)",
      "type": "timeseries"
    },
    {
      "datasource": {
        "uid": "$datasource"
      },
      "fieldConfig": {
        "defaults": {
          "color": {
            "mode": "palette-classic"
          },
          "custom": {
            "axisBorderShow": false,
            "axisCenteredZero": false,
            "axisColorMode": "text",
            "axisLabel": "",
            "axisPlacement": "auto",
            "barAlignment": 0,
            "drawStyle": "line",
            "fillOpacity": 10,
            "gradientMode": "none",
            "hideFrom": {
              "legend": false,
              "tooltip": false,
              "viz": false
            },
            "insertNulls": false,
            "lineInterpolation": "linear",
            "lineWidth": 1,
            "pointSize": 5,
            "scaleDistribution": {
              "type": "linear"
            },
            "showPoints": "never",
            "spanNulls": false,
            "stacking": {
              "group": "A",
              "mode": "none"
            },
            "thresholdsStyle": {
              "mode": "off"
            }
          },
          "mappings": [],
          "thresholds": {
            "mode": "absolute",
            "steps": [
              {
                "color": "green",
                "value": null
              },
              {
                "color": "red",
                "value": 80
              }
            ]
          },
          "unit": "percentunit"
        },
        "overrides": []
      },
      "gridPos": {
        "h": 9,
        "w": 24,
        "x": 0,
        "y": 51
      },
      "id": 36,
      "options": {
        "legend": {
          "calcs": [],
          "displayMode": "list",
          "placement": "bottom",
          "showLegend": true
        },
        "tooltip": {
          "mode": "multi",
          "sort": "desc"
        }
      },
      "pluginVersion": "10.4.1",
      "targets": [
        {
          "application": {
            "filter": ""
          },
          "datasource": {
            "uid": "$datasource"
          },
          "exemplar": true,
          "expr": "sum(rate(http_requests_total{job=~\"$job\",instance=~\"$instance\", path=~\"$handler\", namespace=~\"$namespace\", status=\"500|502|503|504\"}[5m])) by (job, method, handler)/sum(rate(http_requests_total{job=~\"$job\",instance=~\"$instance\", path=~\"$handler\", namespace=~\"$namespace\"}[5m])) by (job, method, handler)",
          "format": "time_series",
          "functions": [],
          "group": {
            "filter": ""
          },
          "host": {
            "filter": ""
          },
          "instant": false,
          "interval": "",
          "intervalFactor": 1,
          "item": {
            "filter": ""
          },
          "legendFormat": "{{ job }} - {{ method }} {{handler}}",
          "mode": 0,
          "options": {
            "showDisabledItems": false,
            "skipEmptyValues": false
          },
          "refId": "A",
          "resultFormat": "time_series",
          "table": {
            "skipEmptyValues": false
          },
          "triggers": {
            "acknowledged": 2,
            "count": true,
            "minSeverity": 3
          }
        }
      ],
      "title": "Errors - % by handler (5xx)",
      "type": "timeseries"
    },
    {
      "collapsed": false,
      "datasource": {
        "type": "prometheus",
        "uid": "P3CCD15422F6EB158"
      },
      "gridPos": {
        "h": 1,
        "w": 24,
        "x": 0,
        "y": 60
      },
      "id": 45,
      "panels": [],
      "targets": [
        {
          "datasource": {
            "type": "prometheus",
            "uid": "P3CCD15422F6EB158"
          },
          "refId": "A"
        }
      ],
      "title": "Latêncy",
      "type": "row"
    },
    {
      "datasource": {
        "type": "prometheus",
        "uid": "$datasource"
      },
      "fieldConfig": {
        "defaults": {
          "color": {
            "mode": "palette-classic"
          },
          "custom": {
            "axisBorderShow": false,
            "axisCenteredZero": false,
            "axisColorMode": "text",
            "axisLabel": "",
            "axisPlacement": "auto",
            "barAlignment": 0,
            "drawStyle": "line",
            "fillOpacity": 10,
            "gradientMode": "none",
            "hideFrom": {
              "legend": false,
              "tooltip": false,
              "viz": false
            },
            "insertNulls": false,
            "lineInterpolation": "linear",
            "lineWidth": 1,
            "pointSize": 5,
            "scaleDistribution": {
              "type": "linear"
            },
            "showPoints": "never",
            "spanNulls": false,
            "stacking": {
              "group": "A",
              "mode": "none"
            },
            "thresholdsStyle": {
              "mode": "off"
            }
          },
          "mappings": [],
          "thresholds": {
            "mode": "absolute",
            "steps": [
              {
                "color": "green",
                "value": null
              },
              {
                "color": "red",
                "value": 80
              }
            ]
          },
          "unit": "s"
        },
        "overrides": []
      },
      "gridPos": {
        "h": 9,
        "w": 24,
        "x": 0,
        "y": 61
      },
      "id": 37,
      "options": {
        "legend": {
          "calcs": [],
          "displayMode": "list",
          "placement": "bottom",
          "showLegend": true
        },
        "tooltip": {
          "mode": "multi",
          "sort": "desc"
        }
      },
      "pluginVersion": "10.4.1",
      "targets": [
        {
          "application": {
            "filter": ""
          },
          "datasource": {
            "uid": "$datasource"
          },
          "editorMode": "code",
          "exemplar": true,
          "expr": "histogram_quantile(0.5, sum by (job, le) (rate(http_request_duration_seconds_bucket{job=~\"$job\",instance=~\"$instance\", path=~\"$handler\", namespace=~\"$namespace\"}[5m])))",
          "format": "time_series",
          "functions": [],
          "group": {
            "filter": ""
          },
          "host": {
            "filter": ""
          },
          "instant": false,
          "interval": "",
          "intervalFactor": 1,
          "item": {
            "filter": ""
          },
          "legendFormat": "{{ job }} - p50",
          "mode": 0,
          "options": {
            "showDisabledItems": false,
            "skipEmptyValues": false
          },
          "refId": "A",
          "resultFormat": "time_series",
          "table": {
            "skipEmptyValues": false
          },
          "triggers": {
            "acknowledged": 2,
            "count": true,
            "minSeverity": 3
          }
        },
        {
          "datasource": {
            "uid": "$datasource"
          },
          "exemplar": true,
          "expr": "histogram_quantile(0.95, sum by (job, le) (rate(http_request_duration_seconds_bucket{job=~\"$job\",instance=~\"$instance\", path=~\"$handler\", namespace=~\"$namespace\"}[5m])))",
          "format": "time_series",
          "interval": "",
          "intervalFactor": 1,
          "legendFormat": "{{ job }} - p95",
          "refId": "B"
        },
        {
          "datasource": {
            "uid": "$datasource"
          },
          "exemplar": true,
          "expr": "histogram_quantile(0.99, sum by (job, le) (rate(http_request_duration_seconds_bucket{job=~\"$job\",instance=~\"$instance\", path=~\"$handler\", namespace=~\"$namespace\"}[5m])))",
          "format": "time_series",
          "interval": "",
          "intervalFactor": 1,
          "legendFormat": "{{ job }} - p99",
          "refId": "C"
        }
      ],
      "title": "Latency - General",
      "type": "timeseries"
    },
    {
      "datasource": {
        "uid": "$datasource"
      },
      "fieldConfig": {
        "defaults": {
          "color": {
            "mode": "palette-classic"
          },
          "custom": {
            "axisBorderShow": false,
            "axisCenteredZero": false,
            "axisColorMode": "text",
            "axisLabel": "",
            "axisPlacement": "auto",
            "barAlignment": 0,
            "drawStyle": "line",
            "fillOpacity": 10,
            "gradientMode": "none",
            "hideFrom": {
              "legend": false,
              "tooltip": false,
              "viz": false
            },
            "insertNulls": false,
            "lineInterpolation": "linear",
            "lineWidth": 1,
            "pointSize": 5,
            "scaleDistribution": {
              "type": "linear"
            },
            "showPoints": "never",
            "spanNulls": false,
            "stacking": {
              "group": "A",
              "mode": "none"
            },
            "thresholdsStyle": {
              "mode": "off"
            }
          },
          "mappings": [],
          "thresholds": {
            "mode": "absolute",
            "steps": [
              {
                "color": "green",
                "value": null
              },
              {
                "color": "red",
                "value": 80
              }
            ]
          },
          "unit": "s"
        },
        "overrides": []
      },
      "gridPos": {
        "h": 9,
        "w": 24,
        "x": 0,
        "y": 70
      },
      "id": 38,
      "options": {
        "legend": {
          "calcs": [],
          "displayMode": "list",
          "placement": "bottom",
          "showLegend": true
        },
        "tooltip": {
          "mode": "multi",
          "sort": "desc"
        }
      },
      "pluginVersion": "10.4.1",
      "targets": [
        {
          "application": {
            "filter": ""
          },
          "datasource": {
            "uid": "$datasource"
          },
          "exemplar": true,
          "expr": "histogram_quantile(0.5, sum by (job, method, handler, le) (rate(http_request_duration_seconds_bucket{job=~\"$job\",instance=~\"$instance\", path=~\"$handler\", namespace=~\"$namespace\"}[5m])))",
          "format": "time_series",
          "functions": [],
          "group": {
            "filter": ""
          },
          "host": {
            "filter": ""
          },
          "instant": false,
          "interval": "",
          "intervalFactor": 1,
          "item": {
            "filter": ""
          },
          "legendFormat": "{{ job }} - {{ method }} {{ handler }} - p50",
          "mode": 0,
          "options": {
            "showDisabledItems": false,
            "skipEmptyValues": false
          },
          "refId": "A",
          "resultFormat": "time_series",
          "table": {
            "skipEmptyValues": false
          },
          "triggers": {
            "acknowledged": 2,
            "count": true,
            "minSeverity": 3
          }
        },
        {
          "datasource": {
            "uid": "$datasource"
          },
          "exemplar": true,
          "expr": "histogram_quantile(0.95, sum by (job, method, handler, le) (rate(http_request_duration_seconds_bucket{job=~\"$job\",instance=~\"$instance\", path=~\"$handler\", namespace=~\"$namespace\"}[5m])))",
          "format": "time_series",
          "interval": "",
          "intervalFactor": 1,
          "legendFormat": "{{ job }} - {{ method }} {{ handler }} - p95",
          "refId": "B"
        },
        {
          "datasource": {
            "uid": "$datasource"
          },
          "exemplar": true,
          "expr": "histogram_quantile(0.99, sum by (job, method, handler, le) (rate(http_request_duration_seconds_bucket{job=~\"$job\",instance=~\"$instance\", path=~\"$handler\", namespace=~\"$namespace\"}[5m])))",
          "format": "time_series",
          "interval": "",
          "intervalFactor": 1,
          "legendFormat": "{{ job }} - {{ method }} {{ handler }} - p99",
          "refId": "C"
        }
      ],
      "title": "Latency by handler",
      "type": "timeseries"
    },
    {
      "datasource": {
        "uid": "$datasource"
      },
      "fieldConfig": {
        "defaults": {
          "color": {
            "mode": "palette-classic"
          },
          "custom": {
            "axisBorderShow": false,
            "axisCenteredZero": false,
            "axisColorMode": "text",
            "axisLabel": "",
            "axisPlacement": "auto",
            "barAlignment": 0,
            "drawStyle": "line",
            "fillOpacity": 10,
            "gradientMode": "none",
            "hideFrom": {
              "legend": false,
              "tooltip": false,
              "viz": false
            },
            "insertNulls": false,
            "lineInterpolation": "linear",
            "lineWidth": 1,
            "pointSize": 5,
            "scaleDistribution": {
              "type": "linear"
            },
            "showPoints": "never",
            "spanNulls": false,
            "stacking": {
              "group": "A",
              "mode": "none"
            },
            "thresholdsStyle": {
              "mode": "off"
            }
          },
          "mappings": [],
          "thresholds": {
            "mode": "absolute",
            "steps": [
              {
                "color": "green",
                "value": null
              },
              {
                "color": "red",
                "value": 80
              }
            ]
          },
          "unit": "s"
        },
        "overrides": []
      },
      "gridPos": {
        "h": 9,
        "w": 24,
        "x": 0,
        "y": 79
      },
      "id": 39,
      "options": {
        "legend": {
          "calcs": [],
          "displayMode": "list",
          "placement": "bottom",
          "showLegend": true
        },
        "tooltip": {
          "mode": "multi",
          "sort": "desc"
        }
      },
      "pluginVersion": "10.4.1",
      "targets": [
        {
          "application": {
            "filter": ""
          },
          "datasource": {
            "uid": "$datasource"
          },
          "exemplar": true,
          "expr": "histogram_quantile(0.5, sum by (job, instance, le) (rate(http_request_duration_seconds_bucket{job=~\"$job\",instance=~\"$instance\", path=~\"$handler\", namespace=~\"$namespace\"}[5m])))",
          "format": "time_series",
          "functions": [],
          "group": {
            "filter": ""
          },
          "host": {
            "filter": ""
          },
          "instant": false,
          "interval": "",
          "intervalFactor": 1,
          "item": {
            "filter": ""
          },
          "legendFormat": "{{ job }} - {{ instance }} - p50",
          "mode": 0,
          "options": {
            "showDisabledItems": false,
            "skipEmptyValues": false
          },
          "refId": "A",
          "resultFormat": "time_series",
          "table": {
            "skipEmptyValues": false
          },
          "triggers": {
            "acknowledged": 2,
            "count": true,
            "minSeverity": 3
          }
        },
        {
          "datasource": {
            "uid": "$datasource"
          },
          "exemplar": true,
          "expr": "histogram_quantile(0.95, sum by (job, instance, le) (rate(http_request_duration_seconds_bucket{job=~\"$job\",instance=~\"$instance\", path=~\"$handler\", namespace=~\"$namespace\"}[5m])))",
          "format": "time_series",
          "interval": "",
          "intervalFactor": 1,
          "legendFormat": "{{ job }} - {{ instance }} - p95",
          "refId": "B"
        },
        {
          "datasource": {
            "uid": "$datasource"
          },
          "exemplar": true,
          "expr": "histogram_quantile(0.99, sum by (job, instance, le) (rate(http_request_duration_seconds_bucket{job=~\"$job\",instance=~\"$instance\", path=~\"$handler\", namespace=~\"$namespace\"}[5m])))",
          "format": "time_series",
          "interval": "",
          "intervalFactor": 1,
          "legendFormat": "{{ job }} - {{ instance }} - p99",
          "refId": "C"
        }
      ],
      "title": "Latency by instance",
      "type": "timeseries"
    },
    {
      "datasource": {
        "uid": "$datasource"
      },
      "fieldConfig": {
        "defaults": {
          "color": {
            "mode": "palette-classic"
          },
          "custom": {
            "axisBorderShow": false,
            "axisCenteredZero": false,
            "axisColorMode": "text",
            "axisLabel": "",
            "axisPlacement": "auto",
            "barAlignment": 0,
            "drawStyle": "line",
            "fillOpacity": 10,
            "gradientMode": "none",
            "hideFrom": {
              "legend": false,
              "tooltip": false,
              "viz": false
            },
            "insertNulls": false,
            "lineInterpolation": "linear",
            "lineWidth": 1,
            "pointSize": 5,
            "scaleDistribution": {
              "type": "linear"
            },
            "showPoints": "never",
            "spanNulls": false,
            "stacking": {
              "group": "A",
              "mode": "none"
            },
            "thresholdsStyle": {
              "mode": "off"
            }
          },
          "mappings": [],
          "thresholds": {
            "mode": "absolute",
            "steps": [
              {
                "color": "green",
                "value": null
              },
              {
                "color": "red",
                "value": 80
              }
            ]
          },
          "unit": "s"
        },
        "overrides": []
      },
      "gridPos": {
        "h": 9,
        "w": 24,
        "x": 0,
        "y": 88
      },
      "id": 47,
      "options": {
        "legend": {
          "calcs": [],
          "displayMode": "list",
          "placement": "bottom",
          "showLegend": true
        },
        "tooltip": {
          "mode": "multi",
          "sort": "desc"
        }
      },
      "pluginVersion": "10.4.1",
      "targets": [
        {
          "datasource": {
            "uid": "$datasource"
          },
          "exemplar": true,
          "expr": "histogram_quantile(0.99, sum by (job, instance, le) (rate(http_request_duration_seconds_bucket{job=~\"$job\",instance=~\"$instance\", path=~\"$handler\", namespace=~\"$namespace\"}[5m])))",
          "format": "time_series",
          "interval": "",
          "intervalFactor": 1,
          "legendFormat": "{{ job }} - {{ instance }} - p99",
          "refId": "C"
        }
      ],
      "title": "Latency 99p by instance",
      "type": "timeseries"
    }
  ],
  "refresh": "5s",
  "schemaVersion": 39,
  "tags": [],
  "templating": {
    "list": [
      {
        "current": {
          "selected": false,
          "text": "prometheus-main",
          "value": "P3CCD15422F6EB158"
        },
        "hide": 0,
        "includeAll": false,
        "label": "DataSource",
        "multi": false,
        "name": "datasource",
        "options": [],
        "query": "prometheus",
        "queryValue": "",
        "refresh": 1,
        "regex": "",
        "skipUrlSync": false,
        "type": "datasource"
      },
      {
        "current": {
          "selected": false,
          "text": "All",
          "value": "$__all"
        },
        "datasource": {
          "uid": "$datasource"
        },
        "definition": "label_values(http_requests_total, namespace)",
        "hide": 0,
        "includeAll": true,
        "label": "Namespace",
        "multi": false,
        "name": "namespace",
        "options": [],
        "query": {
          "query": "label_values(http_requests_total, namespace)",
          "refId": "StandardVariableQuery"
        },
        "refresh": 1,
        "regex": "",
        "skipUrlSync": false,
        "sort": 1,
        "tagValuesQuery": "",
        "tagsQuery": "",
        "type": "query",
        "useTags": false
      },
      {
        "current": {
          "selected": false,
          "text": "All",
          "value": "$__all"
        },
        "datasource": {
          "uid": "$datasource"
        },
        "definition": "label_values(http_requests_total, job)",
        "hide": 0,
        "includeAll": true,
        "label": "Job",
        "multi": false,
        "name": "job",
        "options": [],
        "query": {
          "query": "label_values(http_requests_total, job)",
          "refId": "StandardVariableQuery"
        },
        "refresh": 1,
        "regex": "",
        "skipUrlSync": false,
        "sort": 1,
        "tagValuesQuery": "",
        "tagsQuery": "",
        "type": "query",
        "useTags": false
      },
      {
        "current": {
          "selected": false,
          "text": "All",
          "value": "$__all"
        },
        "datasource": {
          "uid": "$datasource"
        },
        "definition": "label_values(http_requests_total, instance)",
        "hide": 0,
        "includeAll": true,
        "label": "Instance",
        "multi": false,
        "name": "instance",
        "options": [],
        "query": {
          "query": "label_values(http_requests_total, instance)",
          "refId": "StandardVariableQuery"
        },
        "refresh": 1,
        "regex": "",
        "skipUrlSync": false,
        "sort": 1,
        "tagValuesQuery": "",
        "tagsQuery": "",
        "type": "query",
        "useTags": false
      },
      {
        "current": {
          "selected": false,
          "text": "All",
          "value": "$__all"
        },
        "datasource": {
          "uid": "$datasource"
        },
        "definition": "label_values(http_requests_total, path)",
        "hide": 0,
        "includeAll": true,
        "label": "Handler",
        "multi": false,
        "name": "handler",
        "options": [],
        "query": {
          "query": "label_values(http_requests_total, path)",
          "refId": "StandardVariableQuery"
        },
        "refresh": 1,
        "regex": "",
        "skipUrlSync": false,
        "sort": 1,
        "tagValuesQuery": "",
        "tagsQuery": "",
        "type": "query",
        "useTags": false
      }
    ]
  },
  "time": {
    "from": "now-15m",
    "to": "now"
  },
  "timepicker": {
    "refresh_intervals": [
      "5s",
      "10s",
      "30s",
      "1m",
      "5m",
      "15m",
      "30m",
      "1h",
      "2h",
      "1d"
    ],
    "time_options": [
      "5m",
      "15m",
      "1h",
      "6h",
      "12h",
      "24h",
      "2d",
      "7d",
      "30d"
    ]
  },
  "timezone": "browser",
  "title": "OpenIdea Bank App",
  "uid": "9bnfeorMz",
  "version": 3,
  "weekStart": ""
}